pyzstd/__init__.py
pyzstd/__main__.py
pyzstd/_seekable_zstdfile.py
pyzstd/_version.py
pyzstd/py.typed
pyzstd-0.19.0.dist-info/METADATA
pyzstd-0.19.0.dist-info/WHEEL
pyzstd-0.19.0.dist-info/licenses/LICENSE
pyzstd-0.19.0.dist-info/RECORD
