Metadata-Version: 2.4
Name: pyzstd
Version: 0.19.0
Summary: Support for Zstandard (zstd) compression
Project-URL: Homepage, https://github.com/Rogdham/pyzstd
Project-URL: Documentation, https://pyzstd.readthedocs.io/
Project-URL: Source, https://github.com/Rogdham/pyzstd
Author-email: Ma Lin <malincns@163.com>, Rogdham <contact@rogdham.net>
Maintainer-email: Rogdham <contact@rogdham.net>
License-Expression: BSD-3-Clause
License-File: LICENSE
Keywords: compress,decompress,file,seek,seekable,tar,zst,zstandard,zstd
Classifier: Development Status :: 5 - Production/Stable
Classifier: Intended Audience :: Developers
Classifier: License :: OSI Approved :: BSD License
Classifier: Operating System :: OS Independent
Classifier: Programming Language :: Python :: 3.10
Classifier: Programming Language :: Python :: 3.11
Classifier: Programming Language :: Python :: 3.12
Classifier: Programming Language :: Python :: 3.13
Classifier: Programming Language :: Python :: 3.14
Classifier: Topic :: System :: Archiving :: Compression
Requires-Python: >=3.10
Requires-Dist: backports-zstd>=1.0.0; python_version < '3.14'
Requires-Dist: typing-extensions>=4.13.2; python_version < '3.13'
